MANIFEST.in
README.rst
requirements.txt
setup.cfg
setup.py
django_microsip_diot/__init__.py
django_microsip_diot/__init__.pyc
django_microsip_diot/autocomplete_light_registry.pyc
django_microsip_diot/config.pyc
django_microsip_diot/forms.pyc
django_microsip_diot/models.pyc
django_microsip_diot/urls.pyc
django_microsip_diot/views.pyc
django_microsip_diot.egg-info/PKG-INFO
django_microsip_diot.egg-info/SOURCES.txt
django_microsip_diot.egg-info/dependency_links.txt
django_microsip_diot.egg-info/requires.txt
django_microsip_diot.egg-info/top_level.txt
django_microsip_diot/custom_db/__init__.py
django_microsip_diot/custom_db/__init__.pyc
django_microsip_diot/custom_db/paises.pyc
django_microsip_diot/custom_db/procedures.pyc
django_microsip_diot/custom_db/report_builder.pyc
django_microsip_diot/static/django_microsip_diot/css/style.css
django_microsip_diot/static/django_microsip_diot/css/fileupload/blueimp-gallery.min.css
django_microsip_diot/static/django_microsip_diot/css/fileupload/demo-ie8.css
django_microsip_diot/static/django_microsip_diot/css/fileupload/demo.css
django_microsip_diot/static/django_microsip_diot/css/fileupload/jquery.fileupload-ui-noscript.css
django_microsip_diot/static/django_microsip_diot/css/fileupload/jquery.fileupload-ui.css
django_microsip_diot/static/django_microsip_diot/css/fileupload/style.css
django_microsip_diot/static/django_microsip_diot/js/base.js
django_microsip_diot/static/django_microsip_diot/js/diot.js
django_microsip_diot/static/django_microsip_diot/js/importar_xml.js
django_microsip_diot/static/django_microsip_diot/js/inicializa.js
django_microsip_diot/static/django_microsip_diot/js/fileupload/app.js
django_microsip_diot/static/django_microsip_diot/js/fileupload/bootstrap.min.js
django_microsip_diot/static/django_microsip_diot/js/fileupload/canvas-to-blob.min.js
django_microsip_diot/static/django_microsip_diot/js/fileupload/csrf.js
django_microsip_diot/static/django_microsip_diot/js/fileupload/jquery.blueimp-gallery.min.js
django_microsip_diot/static/django_microsip_diot/js/fileupload/jquery.cookie.js
django_microsip_diot/static/django_microsip_diot/js/fileupload/jquery.fileupload-angular.js
