Metadata-Version: 1.1
Name: django-microsip-diot
Version: 1.6.8
Summary: Generacion de DIOT Contabilidad Microsip
Home-page: UNKNOWN
Author: Servicios de Ingenieria Computacional
Author-email: felixfhdez15@gmail.com
License: BSD License
Platform: UNKNOWN
Classifier: Environment :: Web Environment
Classifier: Framework :: Django
Classifier: Intended Audience :: Developers
Classifier: License :: OSI Approved :: BSD License
Classifier: Operating System :: OS Independent
Classifier: Programming Language :: Python
Classifier: Programming Language :: Python :: 2.6
Classifier: Programming Language :: Python :: 2.7
Classifier: Topic :: Internet :: WWW/HTTP
Classifier: Topic :: Internet :: WWW/HTTP :: Dynamic Content
